happy_little_helpers/__init__.py
happy_little_helpers/debugger.py
happy_little_helpers/flash_env.py
happy_little_helpers-0.0.3.dist-info/LICENSE
happy_little_helpers-0.0.3.dist-info/METADATA
happy_little_helpers-0.0.3.dist-info/WHEEL
happy_little_helpers-0.0.3.dist-info/top_level.txt
happy_little_helpers-0.0.3.dist-info/RECORD
