Metadata-Version: 2.1
Name: happy-little-helpers
Version: 0.0.3
Summary: a collection of happy little helpers.
Author-email: wyattlovesgrapes <wyattlovesgrapes@gmail.com>
Project-URL: Homepage, https://github.com/wyattlovesgrapes/happy-little-helpers
Classifier: Programming Language :: Python :: 3
Classifier: License :: OSI Approved :: MIT License
Classifier: Operating System :: OS Independent
Requires-Python: >=3.6
License-File: LICENSE
